Combinational_Circuits/Half_Adder_Circuit/half_adder.v
module half_adder(sum,carry,a,b);
    output sum,carry;
    input a,b;
    xor x1(sum,a,b);
    and a1(carry,a,b);
endmodule

Combinational_Circuits/Full_Adder_Using_Half_Adder/fa_using_ha_tb.v
`include "half_adder.v"
module fa_using_ha_tb;
    reg a,b,cin;
    wire sum,cout;

    wire ha_1_s,ha_1_c;
    wire has_2_c;

    half_adder ha1(ha_1_s,ha_1_c,a,b);
    half_adder ha2(sum,has_2_c,cin,ha_1_s);
    or o1(cout,ha_1_c,has_2_c);

    initial begin
        $dumpfile("fa_using_ha_tb.vcd");
        $dumpvars(0,fa_using_ha_tb);
        a=0;b=0;cin=0;
        #1
        a=0;b=0;cin=1;
        #1
        a=0;b=1;cin=0;
        #1
        a=0;b=1;cin=1;
        #1
        a=1;b=0;cin=0;
        #1
        a=1;b=0;cin=1;
        #1
        a=1;b=1;cin=0;
        #1
        a=1;b=1;cin=1;
    end
endmodule

Combinational_Circuits/Full_Adder_Using_Half_Adder/fa_using_ha_tb.vcd
$date
	Sun Aug 18 22:10:59 2024
$end
$version
	Icarus Verilog
$end
$timescale
	1s
$end
$scope module fa_using_ha_tb $end
$var wire 1 ! cout $end
$var wire 1 " ha_1_c $end
$var wire 1 # ha_1_s $end
$var wire 1 $ has_2_c $end
$var wire 1 % sum $end
$var reg 1 & a $end
$var reg 1 ' b $end
$var reg 1 ( cin $end
$scope module ha1 $end
$var wire 1 ) a $end
$var wire 1 * b $end
$var wire 1 " carry $end
$var wire 1 # sum $end
$upscope $end
$scope module ha2 $end
$var wire 1 + a $end
$var wire 1 # b $end
$var wire 1 $ carry $end
$var wire 1 % sum $end
$upscope $end
$upscope $end
$enddefinitions $end
#0
$dumpvars
0+
0*
0)
0(
0'
0&
0%
0$
0#
0"
0!
$end
#1
1%
1(
1+
#2
1#
0(
0+
1'
1*
#3
1!
0%
1$
1(
1+
#4
0!
1%
0$
0(
0+
0'
0*
1&
1)
#5
1!
0%
1$
1(
1+
#6
0$
0#
1"
0(
0+
1'
1*
#7
1%
1(
1+
