Combinational_Circuits/fs_using_hs/half_sub.v
module half_sub(diff,borrow,a,b);
    input a,b;
    output diff,borrow;
    wire a_not;
    xor x1(diff,a,b);
    not n1(a_not,a);
    and a1(borrow,a_not,b);
endmodule

Combinational_Circuits/fs_using_hs/fs_hs_tb.v
`timescale 1ns/1ps
`include "half_sub.v"
module fs_hs_tb;
    reg a,b,bi;
    wire hs1_d,hs1_b,diff,hs2_c,borrow;

    half_sub ha1(.diff(hs1_d),.a(a),.b(b),.borrow(hs1_b));
    half_sub ha2(.diff(diff),.borrow(hs2_c),.a(hs1_d),.b(bi));
    or o1(borrow,hs1_b,hs2_c);

    initial begin
        $dumpfile("fs_hs.vcd");
        $dumpvars(0,fs_hs_tb);
        a=0;b=0;bi=0; #10
        a=0;b=0;bi=1; #10
        a=0;b=1;bi=0; #10
        a=0;b=1;bi=1; #10
        a=1;b=0;bi=0; #10
        a=1;b=0;bi=1; #10
        a=1;b=1;bi=0; #10
        a=1;b=1;bi=1; #10
        #10 $finish;
    end

endmodule

Combinational_Circuits/fs_using_hs/fs_hs.vcd
$date
	Mon Aug 19 19:33:58 2024
$end
$version
	Icarus Verilog
$end
$timescale
	1ps
$end
$scope module fs_hs_tb $end
$var wire 1 ! borrow $end
$var wire 1 " diff $end
$var wire 1 # hs1_b $end
$var wire 1 $ hs1_d $end
$var wire 1 % hs2_c $end
$var reg 1 & a $end
$var reg 1 ' b $end
$var reg 1 ( bi $end
$scope module ha1 $end
$var wire 1 ) a $end
$var wire 1 * a_not $end
$var wire 1 + b $end
$var wire 1 # borrow $end
$var wire 1 $ diff $end
$upscope $end
$scope module ha2 $end
$var wire 1 $ a $end
$var wire 1 , a_not $end
$var wire 1 - b $end
$var wire 1 % borrow $end
$var wire 1 " diff $end
$upscope $end
$upscope $end
$enddefinitions $end
#0
$dumpvars
0-
1,
0+
1*
0)
0(
0'
0&
0%
0$
0#
0"
0!
$end
#10000
1!
1"
1%
1(
1-
#20000
0,
0%
1$
1#
0(
0-
1'
1+
#30000
0"
1(
1-
#40000
0!
1"
0#
0*
0(
0-
0'
0+
1&
1)
#50000
0"
1(
1-
#60000
1,
0$
0(
0-
1'
1+
#70000
1!
1"
1%
1(
1-
