Combinational_Circuits/Full_Adder_Circuit/full_adder.v
module full_adder(sum,cout,a,b,cin);
    output sum,cout;
    input a,b,cin;
    wire in_xor,in_and,x1_and;
    
    xor x1(in_xor,a,b);
    xor x2(sum,in_xor,cin);
    
    and a1(in_and,a,b);
    and a2(x1_and,cin);

    or o1(cout,in_and,x1_and);

endmodule

Combinational_Circuits/Full_Adder_Circuit/full_adder_tb.v
`include "full_adder.v"
module full_adder_tb;
    reg in1,in2,int3c;
    wire sum,cout;

    full_adder fadd1(sum,cout,in1,in2,int3c);
    initial begin
        $dumpfile("full_adder.vcd");
        $dumpvars(0,full_adder_tb);
        in1=0;in2=0;int3c=0;
        #1
        in1=0;in2=0;int3c=1;
        #1
        in1=0;in2=1;int3c=0;
        #1
        in1=0;in2=1;int3c=1;
        #1
        in1=1;in2=0;int3c=0;
        #1
        in1=1;in2=0;int3c=1;
        #1
        in1=1;in2=1;int3c=0;
        #1
        in1=1;in2=1;int3c=1;
    end
endmodule

Combinational_Circuits/Full_Adder_Circuit/full_adder.vcd
$date
	Sun Aug 18 21:32:33 2024
$end
$version
	Icarus Verilog
$end
$timescale
	1s
$end
$scope module full_adder_tb $end
$var wire 1 ! cout $end
$var wire 1 " sum $end
$var reg 1 # in1 $end
$var reg 1 $ in2 $end
$var reg 1 % int3c $end
$scope module fadd1 $end
$var wire 1 & a $end
$var wire 1 ' b $end
$var wire 1 ( cin $end
$var wire 1 ! cout $end
$var wire 1 ) in_and $end
$var wire 1 * in_xor $end
$var wire 1 " sum $end
$var wire 1 + x1_and $end
$upscope $end
$upscope $end
$enddefinitions $end
#0
$dumpvars
0+
0*
0)
0(
0'
0&
0%
0$
0#
0"
0!
$end
#1
1!
1"
1+
1%
1(
#2
0!
0+
1*
0%
0(
1$
1'
#3
1!
0"
1+
1%
1(
#4
0!
1"
0+
0%
0(
0$
0'
1#
1&
#5
1!
0"
1+
1%
1(
#6
0+
0*
1)
0%
0(
1$
1'
#7
1"
1+
1%
1(
