Combinational_Circuits/Full_Subtractor_Circuit/full_sub.v
module full_sub(diff,borrow,a,b,boin);
    input a,b,boin;
    output diff,borrow;
    assign diff = (a^b^boin);
    assign borrow = (boin&~(a^b))|(~a&b);
endmodule

Combinational_Circuits/Full_Subtractor_Circuit/full_sub_tb.v
`timescale 1ns/1ps
`include "full_sub.v"
module full_sub_tb;
    reg a,b,bi;
    wire diff,borrow;

    full_sub fs1(.diff(diff),.a(a),.b(b),.boin(bi),.borrow(borrow));

    initial begin
        $dumpfile("full_sub.vcd");
        $dumpvars(0,full_sub_tb);
        a=0;b=0;bi=0; #10
        a=0;b=0;bi=1; #10
        a=0;b=1;bi=0; #10
        a=0;b=1;bi=1; #10
        a=1;b=0;bi=0; #10
        a=1;b=0;bi=1; #10
        a=1;b=1;bi=0; #10
        a=1;b=1;bi=1; #10
        #10 $finish;
    end
endmodule

Combinational_Circuits/Full_Subtractor_Circuit/full_sub.vcd
$date
	Mon Aug 19 18:40:58 2024
$end
$version
	Icarus Verilog
$end
$timescale
	1ps
$end
$scope module full_sub_tb $end
$var wire 1 ! borrow $end
$var wire 1 " diff $end
$var reg 1 # a $end
$var reg 1 $ b $end
$var reg 1 % bi $end
$scope module fs1 $end
$var wire 1 & a $end
$var wire 1 ' b $end
$var wire 1 ( boin $end
$var wire 1 ! borrow $end
$var wire 1 " diff $end
$upscope $end
$upscope $end
$enddefinitions $end
#0
$dumpvars
0(
0'
0&
0%
0$
0#
0"
0!
$end
#10000
1!
1"
1%
1(
#20000
0%
0(
1$
1'
#30000
0"
1%
1(
#40000
0!
1"
0%
0(
0$
0'
1#
1&
#50000
0"
1%
1(
#60000
0%
0(
1$
1'
#70000
1!
1"
1%
1(
